openerp_pastertemplates
