Metadata-Version: 1.0
Name: openerp-pastertemplates
Version: 1.0a4
Summary: Paster template for creating new OpenERP modules
Home-page: UNKNOWN
Author: Simone Orsi
Author-email: simahawk@gmail.com
License: UNKNOWN
Keywords: OpenERP paster
Platform: UNKNOWN
